django_xtc-0.2.0.dist-info/DESCRIPTION.rst
django_xtc-0.2.0.dist-info/METADATA
django_xtc-0.2.0.dist-info/RECORD
django_xtc-0.2.0.dist-info/WHEEL
django_xtc-0.2.0.dist-info/metadata.json
django_xtc-0.2.0.dist-info/top_level.txt
xtc/__init__.py
xtc/apps.py
xtc/exceptions.py
xtc/mixins.py
xtc/tests.py
xtc/migrations/__init__.py
