Metadata-Version: 2.0
Name: django-xtc
Version: 0.2.0
Summary: eXtra Test Cases for Django
Home-page: http://github.com/melvyn-sopacua/django_xtc
Author: UNKNOWN
Author-email: UNKNOWN
License: BSD 2-Clause License
Requires-Dist: Django (>=1.9)
Provides-Extra: contributor
Requires-Dist: coverage (>=4.4.1); extra == 'contributor'
Requires-Dist: sphinx (>=1.6); extra == 'contributor'
Requires-Dist: twine; extra == 'contributor'
Provides-Extra: docs
Requires-Dist: sphinx (>=1.6); extra == 'docs'
Provides-Extra: rtd
Requires-Dist: sphinx (>=1.6); extra == 'rtd'
Requires-Dist: sphinx-rtd-theme; extra == 'rtd'
